human_math/__init__.py
human_math/__main__.py
human_math/parser/__init__.py
human_math/parser/parse.py
human_math/parser/processors.py
human_math/parser/token_processor.py
human_math/parser/tokens.py
human_math/symbolics/__init__.py
human_math/symbolics/functions.py
human_math/symbolics/nodes.py
human_math/symbolics/operators.py
human_math/tokens/__init__.py
human_math/tokens/kind.py
human_math/tokens/tokenize.py
human_math-0.1.dist-info/LICENSE.md
human_math-0.1.dist-info/WHEEL
human_math-0.1.dist-info/METADATA
human_math-0.1.dist-info/RECORD
