Metadata-Version: 2.1
Name: human_math
Version: 0.1
Summary: Structured math expression representation & parsing.
Keywords: parser,math,maths,expression,token
Author: anatom3000
Requires-Python: >=3.7
Classifier: Development Status :: 4 - Beta
Classifier: License :: OSI Approved :: GNU Lesser General Public License v3 (LGPLv3)
Classifier: Programming Language :: Python :: 3
Classifier: Operating System :: OS Independent
Classifier: Topic :: Scientific/Engineering :: Mathematics
Classifier: Topic :: Text Processing
Classifier: Typing :: Typed
Project-URL: Issues, https://github.com/anatom3000/human_math/issues
Project-URL: Source, https://github.com/anatom3000/human_math
